mintyper/__init__.py
mintyper/ccphylo.py
mintyper/findBestTemplate.py
mintyper/kma.py
mintyper/mintyperPipeline.py
mintyper/validateInput.py
mintyper/version.py
mintyper-1.1.2.data/scripts/mintyper
mintyper-1.1.2.dist-info/METADATA
mintyper-1.1.2.dist-info/WHEEL
mintyper-1.1.2.dist-info/top_level.txt
mintyper-1.1.2.dist-info/RECORD
