Metadata-Version: 2.1
Name: mintyper
Version: 1.1.2
Summary: mintyper: an outbreak-detection method for accurate and rapid SNP typing of clonal clusters with noisy long reads.
Home-page: https://github.com/MBHallgren/mintyper
Author: Malte B. Hallgren
Author-email: malhal@food.dtu.dk
License: MIT
Classifier: Programming Language :: Python :: 3
Classifier: License :: OSI Approved :: MIT License
Classifier: Operating System :: OS Independent
Requires-Python: >=3.6
